extensionNamer/__init__.py
extensionNamer/extensionNamer.py
extensionNamer/extensionNames.json
extensionNamer-0.0.1.dist-info/LICENSE
extensionNamer-0.0.1.dist-info/METADATA
extensionNamer-0.0.1.dist-info/WHEEL
extensionNamer-0.0.1.dist-info/top_level.txt
extensionNamer-0.0.1.dist-info/RECORD
