Metadata-Version: 2.1
Name: extensionNamer
Version: 0.0.1
Home-page: https://github.com/DeshyDan/Extension-Namer
Author: Deshy Dan
License-File: LICENSE
